{
    "product":[
        {
            "name":"Men Round Neck Black T-Shirt",
            "category":"men",
            "accessory":"t-shirt",
            "prize":"345",
            "noOfDaysToDelivery":2,
            "brand":"nike",
            "size":"S",
            "color":"black",
            "image":"../src/assets/images/img01.png",
            "comments":[
            {            
                "rating": 5,
                "comment": "best quality product !!",
                "author": "Md aman Sahil",
                "date": "2020-04-20T17:57:28.556094Z"
            },
            {            
                "rating": 4,
                "comment": "very nice t-shirt I like it",
                "author": "Rohith",
                "date": "2020-04-20T17:57:28.556094Z"
            }
            ]

        },
        {
            "name":"Men Solid Casual Spread Shirt",
            "category":"men",
            "accessory":"shirt",
            "prize":"299",
            "noOfDaysToDelivery":2,
            "brand":"GEUMACCESSORIES",
            "size":"L",
            "color":"yellow",
            "image":"../src/assets/images/img02.png",
            "comments":[
            {            
                "rating": 5,
                "comment": "Superb go for it...",
                "author": "Inder singh Gosain",
                "date": "2020-04-20T17:57:28.556094Z"
            },
            {            
                "rating": 4,
                "comment": "Nice product",
                "author": "Rock star Mohan tej",
                "date": "2020-04-20T17:57:28.556094Z"
            }
            ]

        },
        {
            "name":"Men Printed Casual Button Down Shirt",
            "category":"men",
            "accessory":"Shirt",
            "prize":"549",
            "noOfDaysToDelivery":1,
            "brand":"Highlander ",
            "size":"",
            "color":"Black",
            "image":"../src/assets/images/imgS002.png",
            "comments":[
            {            
                "rating": 1,
                "comment": "worst product ever",
                "author": "Martin",
                "date": "2020-04-20T17:57:28.556094Z"
            }
            ]

        },
        {
            "name":"Striped Men Round Neck White T-Shirt",
            "category":"men",
            "accessory":"Tshirt",
            "prize":"749",
            "noOfDaysToDelivery":4,
            "brand":"United Colors of Benetton ",
            "size":"",
            "color":"White",
            "image":"../src/assets/images/imgS001.png",
            "comments":[
            {            
                "rating": 4,
                "comment": "good product",
                "author": "Inder singh Gosain",
                "date": "2020-04-20T17:57:28.556094Z"
            },
            {            
                "rating": 5,
                "comment": "thats a great product..",
                "author": "Rock star Mohan tej",
                "date": "2020-04-20T17:57:28.556094Z"
            }
            ]

        },
        {
            "name":"Sporty Men Round Neck Red T-Shirt",
            "category":"men",
            "accessory":"Tshirt",
            "prize":"749",
            "noOfDaysToDelivery":7,
            "brand":"ADIDAS",
            "size":"",
            "color":"Red",
            "image":"../src/assets/images/imgS003.png",
            "comments":[
            {            
                "rating": 4,
                "comment": "good product",
                "author": "Inder singh Gosain",
                "date": "2020-04-20T17:57:28.556094Z"
            },
            {            
                "rating": 5,
                "comment": "thats a great product..",
                "author": "Rock star Mohan tej",
                "date": "2020-04-20T17:57:28.556094Z"
            }
            ]

        },
        {
            "name":"Men Printed Jacquard Straight Kurta  (Black)",
            "category":"men",
            "accessory":"Kurtha",
            "prize":"3218",
            "noOfDaysToDelivery":7,
            "brand":"Zois",
            "size":"",
            "color":"Black",
            "image":"../src/assets/images/imgS004.png",
            "comments":[
            {            
                "rating": 5,
                "comment": "best product ever",
                "author": "Marcus",
                "date": "2020-04-20T17:57:28.556094Z"
            },
            {            
                "rating": 5,
                "comment": "thats a great product..",
                "author": " Mohan tej",
                "date": "2020-04-20T17:57:28.556094Z"
            }
            ]

        },
        {
            "name":"Men Floral Print Silk Blend Asymmetric Kurta  (Multicolor)",
            "category":"men",
            "accessory":"Kurtha",
            "prize":"2999",
            "noOfDaysToDelivery":7,
            "brand":"Kishah",
            "size":"",
            "color":"Multicolor",
            "image":"../src/assets/images/imgS005.png",
            "comments":[
            {            
                "rating": 5,
                "comment": "best product ever",
                "author": "Marcus",
                "date": "2020-04-20T17:57:28.556094Z"
            },
            {            
                "rating": 5,
                "comment": "thats a great product..",
                "author": " Mohan tej",
                "date": "2020-04-20T17:57:28.556094Z"
            }
            ]

        },
        
        {
            "name":"Men Printed Cotton Silk Pathani Kurta  (Multicolor)",
            "category":"men",
            "accessory":"Kurtha",
            "prize":"2759",
            "noOfDaysToDelivery":4,
            "brand":"Manyavar ",
            "size":"",
            "color":"Blue",
            "image":"../src/assets/images/imgS007.png",
            "comments":[
            {            
                "rating": 5,
                "comment": "best product ever",
                "author": "Marcus",
                "date": "2020-04-20T17:57:28.556094Z"
            },
            {            
                "rating": 5,
                "comment": "thats a great product..",
                "author": " Mohan tej",
                "date": "2020-04-20T17:57:28.556094Z"
            }
            ]

        },
        {
            "name":"Men Solid Poly Silk Straight Kurta  (Beige)",
            "category":"men",
            "accessory":"Kurtha",
            "prize":"2209",
            "noOfDaysToDelivery":4,
            "brand":"I Know ",
            "size":"",
            "color":"Blue",
            "image":"../src/assets/images/imgS009.png",
            "comments":[
            {            
                "rating": 3,
                "comment": "good one",
                "author": "Marcus",
                "date": "2020-04-20T17:57:28.556094Z"
            },
            {            
                "rating": 5,
                "comment": "thats a great product..",
                "author": " Mohan tej",
                "date": "2020-04-20T17:57:28.556094Z"
            }
            ]

        },
        {
            "name":"Single Breasted Solid Men Suit",
            "category":"men",
            "accessory":"Suit",
            "prize":"13499",
            "noOfDaysToDelivery":4,
            "brand":"Alvin Kelly ",
            "size":"",
            "color":"Black",
            "image":"../src/assets/images/imgS011.png",
            "comments":[
            {            
                "rating": 3,
                "comment": "good one",
                "author": "Marcus",
                "date": "2020-04-20T17:57:28.556094Z"
            },
            {            
                "rating": 5,
                "comment": "thats a great product..",
                "author": " Mohan tej",
                "date": "2020-04-20T17:57:28.556094Z"
            }
            ]

        },
        {
            "name":"Men suit formal",
            "category":"men",
            "accessory":"Suit",
            "prize":"10499",
            "noOfDaysToDelivery":4,
            "brand":"Louis Philippe",
            "size":"",
            "color":"Black",
            "image":"../src/assets/images/imgS012.png",
            "comments":[
            {            
                "rating": 5,
                "comment": "good product",
                "author": "moien",
                "date": "2020-04-20T17:57:28.556094Z"
            },
            {            
                "rating": 5,
                "comment": "thats a great product..",
                "author": " Manoj garu",
                "date": "2020-04-20T17:57:28.556094Z"
            }
        ]
        },
        
        {
            "name":"Suit Solid Men Suit",
            "category":"men",
            "accessory":"Suit",
            "prize":"9009",
            "noOfDaysToDelivery":2,
            "brand":"Arrow",
            "size":"",
            "color":" White",
            "image":"../src/assets/images/imgS014.png",
            "comments":[
            {            
                "rating": 5,
                "comment": "good product",
                "author": "moien",
                "date": "2020-04-20T17:57:28.556094Z"
            },
            {            
                "rating": 5,
                "comment": "thats a great product..",
                "author": " Manoj garu",
                "date": "2020-04-20T17:57:28.556094Z"
            }
        ]
        },
        {
            "name":"Checkered Single Breasted Formal Men Full Sleeve Blazer  (Beige)",
            "category":"men",
            "accessory":"Suit",
            "prize":"7999",
            "noOfDaysToDelivery":2,
            "brand":"Louis Philippe",
            "size":"",
            "color":"Beige",
            "image":"../src/assets/images/imgS015.png",
            "comments":[
            {            
                "rating": 5,
                "comment": "good product",
                "author": "moien",
                "date": "2020-04-20T17:57:28.556094Z"
            },
            {            
                "rating": 5,
                "comment": "thats a great product..",
                "author": " Manoj garu",
                "date": "2020-04-20T17:57:28.556094Z"
            }
        ]
        },
        
        {
            "name":"Tapered Fit Men Blue Jeans",
            "category":"men",
            "accessory":"Jeans",
            "prize":"1499",
            "noOfDaysToDelivery":2,
            "brand":"Flying Machine",
            "size":"",
            "color":"Black",
            "image":"../src/assets/images/imgS017.png",
            "comments":[
            {            
                "rating": 5,
                "comment": "good product",
                "author": "moien",
                "date": "2020-04-20T17:57:28.556094Z"
            },
            {            
                "rating": 5,
                "comment": "good product",
                "author": "mittal",
                "date": "2020-04-20T17:57:28.556094Z"
            },
            {            
                "rating": 5,
                "comment": "thats a great product..",
                "author": " Manoj garu",
                "date": "2020-04-20T17:57:28.556094Z"
            }
        ]
        },
        {
            "name":"Slim Men Dark Blue Jeans",
            "category":"men",
            "accessory":"Jeans",
            "prize":"1499",
            "noOfDaysToDelivery":2,
            "brand":"Metronaut",
            "size":"",
            "color":"Black",
            "image":"../src/assets/images/imgS018.png",
            "comments":[
            {            
                "rating": 3,
                "comment": "good product",
                "author": "moien",
                "date": "2020-04-20T17:57:28.556094Z"
            },
            {            
                "rating": 4,
                "comment": "good product",
                "author": "mittal",
                "date": "2020-04-20T17:57:28.556094Z"
            },
            {            
                "rating": 5,
                "comment": "thats a great product..",
                "author": " Manoj garu",
                "date": "2020-04-20T17:57:28.556094Z"
            }
        ]
        },
        {
            "name":"Slim Men Blue Jeans",
            "category":"men",
            "accessory":"Jeans",
            "prize":"649",
            "noOfDaysToDelivery":2,
            "brand":"Highlander",
            "size":"",
            "color":"Blue",
            "image":"../src/assets/images/imgS019.png",
            "comments":[
            {            
                "rating": 3,
                "comment": "good product",
                "author": "moien",
                "date": "2020-04-20T17:57:28.556094Z"
            },
            {            
                "rating": 4,
                "comment": "good product",
                "author": "mittal",
                "date": "2020-04-20T17:57:28.556094Z"
            },
            {            
                "rating": 5,
                "comment": "thats a great product..",
                "author": " Manoj garu",
                "date": "2020-04-20T17:57:28.556094Z"
            }
        ]
        },
        {
            "name":"Skinny Men Blue Jeans",
            "category":"men",
            "accessory":"Jeans",
            "prize":"1497",
            "noOfDaysToDelivery":2,
            "brand":"Wrangler",
            "size":"",
            "color":"Blue",
            "image":"../src/assets/images/imgS020.png",
            "comments":[
            {            
                "rating": 3,
                "comment": "good product",
                "author": "moien",
                "date": "2020-04-20T17:57:28.556094Z"
            },
            {            
                "rating": 4,
                "comment": "good product",
                "author": "mittal",
                "date": "2020-04-20T17:57:28.556094Z"
            },
            {            
                "rating": 5,
                "comment": "thats a great product..",
                "author": " Manoj garu",
                "date": "2020-04-20T17:57:28.556094Z"
            }
        ]
        },
        {
            "name":"Skinny Men Blue Jeans",
            "category":"men",
            "accessory":"Jeans",
            "prize":"1497",
            "noOfDaysToDelivery":2,
            "brand":"Wrangler",
            "size":"",
            "color":"Blue",
            "image":"../src/assets/images/imgS020.png",
            "comments":[]
        },
        {
            "name":"Skinny Men Blue Jeans",
            "category":"men",
            "accessory":"Jeans",
            "prize":"1197",
            "noOfDaysToDelivery":2,
            "brand":"Peter England",
            "size":"",
            "color":"Blue",
            "image":"../src/assets/images/imgS021.png",
            "comments":[
            {            
                "rating": 3,
                "comment": "good product",
                "author": "moien",
                "date": "2020-04-20T17:57:28.556094Z"
            },
            {            
                "rating": 4,
                "comment": "good product",
                "author": "mittal",
                "date": "2020-04-20T17:57:28.556094Z"
            },
            {            
                "rating": 5,
                "comment": "thats a great product..",
                "author": " Manoj garu",
                "date": "2020-04-20T17:57:28.556094Z"
            }
        ]
        },
        {
            "name":"Skinny Men Blue Jeans",
            "category":"men",
            "accessory":"Jeans",
            "prize":"1624",
            "noOfDaysToDelivery":2,
            "brand":"Peter England",
            "size":"",
            "color":"Blue",
            "image":"../src/assets/images/imgS021.png",
            "comments":[]
        },
        {
            "name":"Slim Fit Men Black Cotton Lycra Blend Trousers",
            "category":"men",
            "accessory":"Trousers",
            "prize":"1886",
            "noOfDaysToDelivery":2,
            "brand":"Highlander",
            "size":"",
            "color":"Black",
            "image":"../src/assets/images/imgS024.png",
            "comments":[
                {            
                    "rating": 3,
                    "comment": "good product",
                    "author": "moien",
                    "date": "2020-04-20T17:57:28.556094Z"
                },
                {            
                    "rating": 4,
                    "comment": "good product",
                    "author": "mittal",
                    "date": "2020-04-20T17:57:28.556094Z"
                },
                {            
                    "rating": 5,
                    "comment": "thats a great product..",
                    "author": " Manoj garu",
                    "date": "2020-04-20T17:57:28.556094Z"
                }
            ]
        },
        {
            "name":"Slim Fit Men Black Polyester Blend Trousers",
            "category":"men",
            "accessory":"Trousers",
            "prize":"979",
            "noOfDaysToDelivery":2,
            "brand":"Peter England",
            "size":"",
            "color":"Black",
            "image":"../src/assets/images/imgS025.png",
            "comments":[
                {            
                    "rating": 3,
                    "comment": "good product",
                    "author": "moien",
                    "date": "2020-04-20T17:57:28.556094Z"
                },
                {            
                    "rating": 4,
                    "comment": "good product",
                    "author": "mittal",
                    "date": "2020-04-20T17:57:28.556094Z"
                },
                {            
                    "rating": 5,
                    "comment": "thats a great product..",
                    "author": " Manoj garu",
                    "date": "2020-04-20T17:57:28.556094Z"
                }
            ]
        },
        {
            "name":"Slim Fit Men Black Polyester Blend Trousers",
            "category":"men",
            "accessory":"Trousers",
            "prize":"979",
            "noOfDaysToDelivery":2,
            "brand":"Raymond",
            "size":"",
            "color":"Black",
            "image":"../src/assets/images/imgS027.png",
            "comments":[
                {            
                    "rating": 3,
                    "comment": "good product",
                    "author": "moien",
                    "date": "2020-04-20T17:57:28.556094Z"
                },
                {            
                    "rating": 4,
                    "comment": "good product",
                    "author": "mittal",
                    "date": "2020-04-20T17:57:28.556094Z"
                },
                {            
                    "rating": 5,
                    "comment": "thats a great product..",
                    "author": " Manoj garu",
                    "date": "2020-04-20T17:57:28.556094Z"
                }
            ]
        },
        {
            "name":"Regular Fit Men Black Pure Cotton Trousers",
            "category":"men",
            "accessory":"Trousers",
            "prize":"989",
            "noOfDaysToDelivery":2,
            "brand":"Arrow",
            "size":"",
            "color":"Black",
            "image":"../src/assets/images/imgS028.png",
            "comments":[
                
                {            
                    "rating": 4,
                    "comment": "good product",
                    "author": "mittal",
                    "date": "2020-04-20T17:57:28.556094Z"
                },
                {            
                    "rating": 5,
                    "comment": "thats a great product..",
                    "author": " Manoj garu",
                    "date": "2020-04-20T17:57:28.556094Z"
                }
            ]
        },
        {
            "name":"Regular Fit Men Grey Cotton Blend Trousers",
            "category":"men",
            "accessory":"Trousers",
            "prize":"1999",
            "noOfDaysToDelivery":2,
            "brand":"Levi's",
            "size":"",
            "color":"White",
            "image":"../src/assets/images/imgS021.png",
            "comments":[
                
                {            
                    "rating": 4,
                    "comment": "good product",
                    "author": "mittal",
                    "date": "2020-04-20T17:57:28.556094Z"
                },
                {            
                    "rating": 5,
                    "comment": "thats a great product..",
                    "author": " Manoj garu",
                    "date": "2020-04-20T17:57:28.556094Z"
                }
            ]
        },
        {
            "name":"Slim Fit Men Dark Green Cotton Blend Trousers",
            "category":"men",
            "accessory":"Trousers",
            "prize":"1999",
            "noOfDaysToDelivery":2,
            "brand":"Arrow",
            "size":"",
            "color":"Green",
            "image":"../src/assets/images/imgS032.png",
            "comments":[
                
                {            
                    "rating": 4,
                    "comment": "good product",
                    "author": "mittal",
                    "date": "2020-04-20T17:57:28.556094Z"
                },
                {            
                    "rating": 5,
                    "comment": "thats a great product..",
                    "author": " Manoj garu",
                    "date": "2020-04-20T17:57:28.556094Z"
                }
            ]
        },
        {
            "name":"Solid Men Grey Sports Shorts",
            "category":"men",
            "accessory":"Shots",
            "prize":"399",
            "noOfDaysToDelivery":2,
            "brand":"Forest Club",
            "size":"",
            "color":"Grey",
            "image":"../src/assets/images/imgS033.png",
            "comments":[
                
                {            
                    "rating": 4,
                    "comment": "good product",
                    "author": "mittal",
                    "date": "2020-04-20T17:57:28.556094Z"
                },
                {            
                    "rating": 5,
                    "comment": "thats a great product..",
                    "author": " Manoj garu",
                    "date": "2020-04-20T17:57:28.556094Z"
                }
            ]
        },
        {
            "name":"Printed, Graphic Print Men White Basic Shorts",
            "category":"men",
            "accessory":"Shots",
            "prize":"299",
            "noOfDaysToDelivery":2,
            "brand":"Hotfits",
            "size":"",
            "color":"White",
            "image":"../src/assets/images/imgS034.png",
            "comments":[
                
                {            
                    "rating": 4,
                    "comment": "good product",
                    "author": "mittal",
                    "date": "2020-04-20T17:57:28.556094Z"
                },
                {            
                    "rating": 5,
                    "comment": "thats a great product..",
                    "author": " Manoj garu",
                    "date": "2020-04-20T17:57:28.556094Z"
                }
            ]
        },
        {
            "name":"Solid Men Black Sports Shorts",
            "category":"men",
            "accessory":"Shots",
            "prize":"1874",
            "noOfDaysToDelivery":2,
            "brand":"Adidas",
            "size":"",
            "color":"Black",
            "image":"../src/assets/images/imgS035.png",
            "comments":[
                
                {            
                    "rating": 4,
                    "comment": "good product",
                    "author": "mittal",
                    "date": "2020-04-20T17:57:28.556094Z"
                },
                {            
                    "rating": 5,
                    "comment": "thats a great product..",
                    "author": " Manoj garu",
                    "date": "2020-04-20T17:57:28.556094Z"
                }
            ]
        },
        {
            "name":"Printed Men Multicolor Chino Shorts",
            "category":"men",
            "accessory":"Shots",
            "prize":"1299",
            "noOfDaysToDelivery":2,
            "brand":"Highlander",
            "size":"",
            "color":"Green",
            "image":"../src/assets/images/imgS037.png",
            "comments":[
                
                {            
                    "rating": 4,
                    "comment": "good product",
                    "author": "mittal",
                    "date": "2020-04-20T17:57:28.556094Z"
                },
                {            
                    "rating": 5,
                    "comment": "thats a great product..",
                    "author": " Manoj garu",
                    "date": "2020-04-20T17:57:28.556094Z"
                }
            ]
        },
        {
            "name":"Self Design Men Grey Sports Shorts",
            "category":"men",
            "accessory":"Shots",
            "prize":"1299",
            "noOfDaysToDelivery":2,
            "brand":"Adidas",
            "size":"",
            "color":"Multicolor",
            "image":"../src/assets/images/imgS038.png",
            "comments":[
                
                {            
                    "rating": 4,
                    "comment": "good product",
                    "author": "mittal",
                    "date": "2020-04-20T17:57:28.556094Z"
                },
                {            
                    "rating": 5,
                    "comment": "thats a great product..",
                    "author": " Manoj garu",
                    "date": "2020-04-20T17:57:28.556094Z"
                }
            ]
        },
        {
            "name":"Printed Men Blue Chino Shorts",
            "category":"men",
            "accessory":"Shots",
            "prize":"1299",
            "noOfDaysToDelivery":2,
            "brand":"Highlander",
            "size":"",
            "color":"Multicolor",
            "image":"../src/assets/images/imgS039.png",
            "comments":[
                
                {            
                    "rating": 4,
                    "comment": "good product",
                    "author": "mittal",
                    "date": "2020-04-20T17:57:28.556094Z"
                },
                {            
                    "rating": 5,
                    "comment": "thats a great product..",
                    "author": " Manoj garu",
                    "date": "2020-04-20T17:57:28.556094Z"
                }
            ]
        },
        {
            "name":"Solid Men Black Track Pants",
            "category":"men",
            "accessory":"Track Pants",
            "prize":"2299",
            "noOfDaysToDelivery":2,
            "brand":"ADIDAS",
            "size":"",
            "color":"Multicolor",
            "image":"../src/assets/images/imgS040.png",
            "comments":[
                
                {            
                    "rating": 4,
                    "comment": "good product",
                    "author": "mittal",
                    "date": "2020-04-20T17:57:28.556094Z"
                },
                {            
                    "rating": 5,
                    "comment": "thats a great product..",
                    "author": " Manoj garu",
                    "date": "2020-04-20T17:57:28.556094Z"
                }
            ]
        },
        {
            "name":"Solid Men Black Track Pants",
            "category":"men",
            "accessory":"Track Pants",
            "prize":"899",
            "noOfDaysToDelivery":2,
            "brand":"Jockey",
            "size":"",
            "color":"Multicolor",
            "image":"../src/assets/images/imgS041.png",
            "comments":[
                
                {            
                    "rating": 4,
                    "comment": "good product",
                    "author": "mittal",
                    "date": "2020-04-20T17:57:28.556094Z"
                },
                {            
                    "rating": 5,
                    "comment": "thats a great product..",
                    "author": " Manoj garu",
                    "date": "2020-04-20T17:57:28.556094Z"
                }
            ]
        },
        {
            "name":"Ultra Solid Men Black Track Pants",
            "category":"men",
            "accessory":"Track Pants",
            "prize":"399",
            "noOfDaysToDelivery":2,
            "brand":"Vimal",
            "size":"",
            "color":"Multicolor",
            "image":"../src/assets/images/imgS042.png",
            "comments":[
                
                {            
                    "rating": 4,
                    "comment": "good product",
                    "author": "mittal",
                    "date": "2020-04-20T17:57:28.556094Z"
                },
                {            
                    "rating": 5,
                    "comment": "thats a great product..",
                    "author": " Manoj garu",
                    "date": "2020-04-20T17:57:28.556094Z"
                }
            ]
        },
        {
            "name":"Solid Men Blue Track Pants",
            "category":"men",
            "accessory":"Track Pants",
            "prize":"2239",
            "noOfDaysToDelivery":2,
            "brand":"U.S. Polo Assn ",
            "size":"",
            "color":"Blue",
            "image":"../src/assets/images/imgS043.png",
            "comments":[
                
                {            
                    "rating": 4,
                    "comment": "good product",
                    "author": "mittal",
                    "date": "2020-04-20T17:57:28.556094Z"
                },
                {            
                    "rating": 5,
                    "comment": "thats a great product..",
                    "author": " Manoj garu",
                    "date": "2020-04-20T17:57:28.556094Z"
                }
            ]
        },
        {
            "name":"Solid Men Black Track Pants",
            "category":"men",
            "accessory":"Track Pants",
            "prize":"1499",
            "noOfDaysToDelivery":2,
            "brand":"Puma ",
            "size":"",
            "color":"Blue",
            "image":"../src/assets/images/imgS044.png",
            "comments":[
                
                {            
                    "rating": 4,
                    "comment": "good product",
                    "author": "mittal",
                    "date": "2020-04-20T17:57:28.556094Z"
                },
                {            
                    "rating": 5,
                    "comment": "thats a great product..",
                    "author": " Manoj garu",
                    "date": "2020-04-20T17:57:28.556094Z"
                }
            ]
        },
        {
            "name":"Color Block Men Dark Green, Black Track Pants",
            "category":"men",
            "accessory":"Track Pants",
            "prize":"499",
            "noOfDaysToDelivery":2,
            "brand":"Metronaut  ",
            "size":"",
            "color":"Brown",
            "image":"../src/assets/images/imgS045.png",
            "comments":[
                
                {            
                    "rating": 4,
                    "comment": "good product",
                    "author": "mittal",
                    "date": "2020-04-20T17:57:28.556094Z"
                },
                {            
                    "rating": 5,
                    "comment": "thats a great product..",
                    "author": " Manoj garu",
                    "date": "2020-04-20T17:57:28.556094Z"
                }
            ]
        },
        {
            "name":"Self Design Men Black Track Pants",
            "category":"men",
            "accessory":"Track Pants",
            "prize":"2099",
            "noOfDaysToDelivery":2,
            "brand":"Reebok",
            "size":"",
            "color":"Black",
            "image":"../src/assets/images/imgS046.png",
            "comments":[
                
                {            
                    "rating": 4,
                    "comment": "good product",
                    "author": "mittal",
                    "date": "2020-04-20T17:57:28.556094Z"
                },
                {            
                    "rating": 5,
                    "comment": "thats a great product..",
                    "author": " Manoj garu",
                    "date": "2020-04-20T17:57:28.556094Z"
                }
            ]
        },
        {
            "name":"Solid Men Light Green Track Pants",
            "category":"men",
            "accessory":"Track Pants",
            "prize":"2099",
            "noOfDaysToDelivery":2,
            "brand":"ADIDAS",
            "size":"",
            "color":"Green",
            "image":"../src/assets/images/imgS047.png",
            "comments":[
                
                
            ]
        },
        {
            "name":"Solid Men Grey Track Pants",
            "category":"men",
            "accessory":"Track Pants",
            "prize":"1916",
            "noOfDaysToDelivery":2,
            "brand":"Nike",
            "size":"",
            "color":"Grey",
            "image":"../src/assets/images/imgS048.png",
            "comments":[
                
                
            ]
        },
        {
            "name":"Embroidered Men Blue Track Pants",
            "category":"men",
            "accessory":"Track Pants",
            "prize":"3999",
            "noOfDaysToDelivery":2,
            "brand":"Tommy Hilfiger",
            "size":"",
            "color":"Blue",
            "image":"../src/assets/images/imgS049.png",
            "comments":[
                
                
            ]
        },
        {
            "name":"Solid Men Grey Track Pants",
            "category":"men",
            "accessory":"Track Pants",
            "prize":"1724",
            "noOfDaysToDelivery":2,
            "brand":"Reebok",
            "size":"",
            "color":"Grey",
            "image":"../src/assets/images/imgS050.png",
            "comments":[
                
                
            ]
        }
    ]

    
}
